vodex/__init__.py
vodex/_version.py
vodex/annotation.py
vodex/core.py
vodex/dbmethods.py
vodex/experiment.py
vodex/loaders.py
vodex/utils.py
vodex/_tests/README.md
vodex/_tests/__init__.py
vodex/_tests/conftest.py
vodex/_tests/test_Cycle.py
vodex/_tests/test_DbExporter.py
vodex/_tests/test_DbReader.py
vodex/_tests/test_DbWriter.py
vodex/_tests/test_Experiment.py
vodex/_tests/test_FileManager.py
vodex/_tests/test_ImageLoader.py
vodex/_tests/test_Labels.py
vodex/_tests/test_Loader.py
vodex/_tests/test_Tiffloader.py
vodex/_tests/test_TimeLabel.py
vodex/_tests/test_Timeline.py
vodex/_tests/test_core.py
vodex/_tests/test_loaders.py
vodex/_tests/data/movie_info.PNG
vodex/_tests/data/test.db
vodex/_tests/data/test_experiment.db
vodex/_tests/data/test_movie.avi
vodex/_tests/data/test_movie.tif
vodex/_tests/data/construction_blocks/data.py
vodex/_tests/data/construction_blocks/numbered_frames.tif
vodex/_tests/data/construction_blocks/recepie.xlsx
vodex/_tests/data/construction_blocks/recepie_long.xlsx
vodex/_tests/data/construction_blocks/zero_frame.tif
vodex/_tests/data/construction_blocks/zero_frame_c1.tif
vodex/_tests/data/construction_blocks/zero_frame_c2.tif
vodex/_tests/data/construction_blocks/zero_frame_c3.tif
vodex/_tests/data/construction_blocks/zero_frame_circle.tif
vodex/_tests/data/construction_blocks/zero_frame_square.tif
vodex/_tests/data/loader_test/frames_1_2_41_42.tif
vodex/_tests/data/loader_test/half_volumes_0_1.tif
vodex/_tests/data/loader_test/half_volumes_1_2.tif
vodex/_tests/data/loader_test/slices_0.tif
vodex/_tests/data/loader_test/slices_0_1.tif
vodex/_tests/data/loader_test/slices_2.tif
vodex/_tests/data/loader_test/volumes_0_1.tif
vodex/_tests/data/loader_test/volumes_0_tail_slices_0_1.tif
vodex/_tests/data/loader_test/volumes_1_2.tif
vodex/_tests/data/loader_test/volumes_tail.tif
vodex/_tests/data/test_movie/mov0.tif
vodex/_tests/data/test_movie/mov1.tif
vodex/_tests/data/test_movie/mov2.tif
vodex-1.0.19.dist-info/METADATA
vodex-1.0.19.dist-info/WHEEL
vodex-1.0.19.dist-info/top_level.txt
vodex-1.0.19.dist-info/RECORD
