Metadata-Version: 2.1
Name: vodex
Version: 1.0.19
Summary: VoDEx : Volumetric Data and Experiment Manager. Allows to load volumetric data based on experimental conditions.
Home-page: https://github.com/LemonJust/vodex
Author: Anna Nadtochiy
Author-email: lemonjustgithub@gmail.com
License: BSD-3-Clause
Project-URL: Bug Tracker, https://github.com/LemonJust/vodex/issues
Project-URL: Documentation, https://github.com/LemonJust/vodex#README.md
Project-URL: Source Code, https://github.com/LemonJust/vodex
Project-URL: User Support, https://github.com/LemonJust/vodex/issues
Classifier: Development Status :: 3 - Alpha
Classifier: Intended Audience :: Science/Research
Classifier: License :: OSI Approved :: BSD License
Classifier: Operating System :: OS Independent
Classifier: Programming Language :: Python
Classifier: Programming Language :: Python :: 3
Classifier: Programming Language :: Python :: 3 :: Only
Classifier: Programming Language :: Python :: 3.8
Classifier: Programming Language :: Python :: 3.9
Classifier: Programming Language :: Python :: 3.10
Classifier: Topic :: Scientific/Engineering :: Image Processing
Requires-Python: >=3.8
Requires-Dist: numpy
Requires-Dist: tifffile
Requires-Dist: tqdm
Requires-Dist: pandas
Provides-Extra: testing
Requires-Dist: tox ; extra == 'testing'
Requires-Dist: pytest ; extra == 'testing'
Requires-Dist: pytest-cov ; extra == 'testing'
